polars_tor-0.2.0.dist-info/METADATA
polars_tor-0.2.0.dist-info/WHEEL
polars_tor/_internal.pyi
polars_tor/typing.py
polars_tor/__init__.py
polars_tor/_internal.abi3.so
polars_tor-0.2.0.dist-info/RECORD
