Metadata-Version: 2.3
Name: polars-tor
Version: 0.2.0
Classifier: Programming Language :: Rust
Classifier: Programming Language :: Python :: Implementation :: CPython
Classifier: Programming Language :: Python :: Implementation :: PyPy
Requires-Dist: maturin >=1.7.4
Requires-Dist: pip >=24.3.1
Requires-Dist: polars >=1.8.2
Requires-Python: >=3.8
